macicons/.DS_Store
macicons/__init__.py
macicons/change_icons.py
macicons/cli.py
macicons/__pycache__/__init__.cpython-310.pyc
macicons/__pycache__/change_icons.cpython-310.pyc
macicons/__pycache__/cli.cpython-310.pyc
macicons/data_files/ignorelist.txt
macicons/data_files/mapper.json
macicons/icons/.DS_Store
macicons/icons/c.png
macicons/icons/cfg.png
macicons/icons/cpp.png
macicons/icons/csharp.png
macicons/icons/csv.png
macicons/icons/cython.png
macicons/icons/fish.png
macicons/icons/git.png
macicons/icons/gitfolder.png
macicons/icons/ini.png
macicons/icons/ipynb.png
macicons/icons/javascript.png
macicons/icons/json.png
macicons/icons/julia.png
macicons/icons/latex.png
macicons/icons/markdown.png
macicons/icons/php.png
macicons/icons/python.png
macicons/icons/r.png
macicons/icons/ruby.png
macicons/icons/toml.png
macicons/icons/txt.png
macicons/icons/typescript.png
macicons/icons/vscode.png
macicons/icons/xml.png
macicons/icons/zig.png
macicons-0.1.1.dist-info/METADATA
macicons-0.1.1.dist-info/WHEEL
macicons-0.1.1.dist-info/entry_points.txt
macicons-0.1.1.dist-info/top_level.txt
macicons-0.1.1.dist-info/RECORD
